cropimage/__init__.py
cropimage/constants.py
cropimage/cropper.py
cropimage-0.0.6.dist-info/LICENSE
cropimage-0.0.6.dist-info/METADATA
cropimage-0.0.6.dist-info/WHEEL
cropimage-0.0.6.dist-info/top_level.txt
cropimage-0.0.6.dist-info/RECORD
