Metadata-Version: 2.1
Name: cropimage
Version: 0.0.6
Summary: A simple toolkit for detecting and cropping main body from pictures.
Home-page: https://github.com/haofanwang/cropimage
Author: Haofan Wang
Author-email: haofanwang.ai@gmail.com
License: UNKNOWN
Platform: UNKNOWN
Classifier: Programming Language :: Python :: 3
Classifier: License :: OSI Approved :: Apache Software License
Classifier: Operating System :: OS Independent
